{"Source Block": ["hdl/library/prcfg/qpsk/prcfg_adc.v@60:70@HdlIdDef", ");\n\n  parameter   CHANNEL_ID    = 0;\n  parameter   DATA_WIDTH    = 32;\n\n  localparam  SYMBOL_WIDTH = 2;\n  localparam  RP_ID         = 8'hA2;\n\n  input                               clk;\n\n  input   [31:0]                      control;\n"], "Clone Blocks": [["hdl/library/prcfg/qpsk/prcfg_adc.v@61:71", "\n  parameter   CHANNEL_ID    = 0;\n  parameter   DATA_WIDTH    = 32;\n\n  localparam  SYMBOL_WIDTH = 2;\n  localparam  RP_ID         = 8'hA2;\n\n  input                               clk;\n\n  input   [31:0]                      control;\n  output  [31:0]                      status;\n"], ["hdl/library/prcfg/qpsk/prcfg_dac.v@62:72", "\n  parameter   CHANNEL_ID    = 0;\n  parameter   DATA_WIDTH    = 32;\n\n  localparam  SYMBOL_WIDTH  = 2;\n  localparam  RP_ID         = 8'hA2;\n\n  input                               clk;\n\n  input   [31:0]                      control;\n  output  [31:0]                      status;\n"], ["hdl/library/prcfg/qpsk/prcfg_dac.v@61:71", ");\n\n  parameter   CHANNEL_ID    = 0;\n  parameter   DATA_WIDTH    = 32;\n\n  localparam  SYMBOL_WIDTH  = 2;\n  localparam  RP_ID         = 8'hA2;\n\n  input                               clk;\n\n  input   [31:0]                      control;\n"]], "Diff Content": {"Delete": [[65, "  localparam  SYMBOL_WIDTH = 2;\n"]], "Add": [[65, "  localparam  SYMBOL_WIDTH  = 2;\n"]]}}