{"Source Block": ["hdl/library/util_wfifo/util_wfifo.v@144:154@HdlStmAssign", "    end\n  end\n\n  // write\n\n  assign fifo_wr = adc_wr;\n\n  genvar m;\n  generate\n  for (m = 0; m < ADC_DATA_WIDTH; m = m + 1) begin: g_wdata\n  assign fifo_wdata[m] = adc_wdata[(ADC_DATA_WIDTH-1)-m];\n"], "Clone Blocks": [["hdl/library/util_wfifo/util_wfifo.v@148:160", "\n  assign fifo_wr = adc_wr;\n\n  genvar m;\n  generate\n  for (m = 0; m < ADC_DATA_WIDTH; m = m + 1) begin: g_wdata\n  assign fifo_wdata[m] = adc_wdata[(ADC_DATA_WIDTH-1)-m];\n  end\n  endgenerate\n\n  // read\n\n  assign dma_wready_s = (DMA_READY_ENABLE == 0) ? 1'b1 : dma_wready;\n"], ["hdl/library/util_wfifo/util_wfifo.v@146:156", "\n  // write\n\n  assign fifo_wr = adc_wr;\n\n  genvar m;\n  generate\n  for (m = 0; m < ADC_DATA_WIDTH; m = m + 1) begin: g_wdata\n  assign fifo_wdata[m] = adc_wdata[(ADC_DATA_WIDTH-1)-m];\n  end\n  endgenerate\n"]], "Diff Content": {"Delete": [[149, "  assign fifo_wr = adc_wr;\n"]], "Add": [[149, "  assign dout_waddr_rel_t_s = dout_waddr_rel_t_m[2] ^ dout_waddr_rel_t_m[1];\n"]]}}