{"Source Block": ["hdl/projects/fmcjesdadc1/a5soc/system_top.v@250:260@HdlIdDef", "  wire              adc0_dovf_s;\n  wire              adc1_enable_a_s;\n  wire    [ 31:0]   adc1_data_a_s;\n  wire              adc1_enable_b_s;\n  wire    [ 31:0]   adc1_data_b_s;\n  wire              adc1_dovf_s;\n  wire    [  3:0]   rx_ip_sof_s;\n  wire    [127:0]   rx_ip_data_s;\n  wire    [127:0]   rx_data_s;\n  wire              rx_sw_rstn_s;\n  wire              rx_sysref_s;\n"], "Clone Blocks": [["hdl/projects/fmcjesdadc1/a5soc/system_top.v@255:265", "  wire              adc1_dovf_s;\n  wire    [  3:0]   rx_ip_sof_s;\n  wire    [127:0]   rx_ip_data_s;\n  wire    [127:0]   rx_data_s;\n  wire              rx_sw_rstn_s;\n  wire              rx_sysref_s;\n  wire              rx_err_s;\n  wire              rx_ready_s;\n  wire    [  3:0]   rx_rst_state_s;\n  wire              rx_lane_aligned_s;\n  wire    [  3:0]   rx_analog_reset_s;\n"], ["hdl/projects/usdrx1/a5gt/system_top.v@264:274", "  wire    [  7:0]   adc_enable_2;\n  wire    [  7:0]   adc_enable_3;\n  wire              adc_dovf_0;\n  wire              adc_dovf_1;\n  wire              adc_dovf_2;\n  wire              adc_dovf_3;\n  wire    [  3:0]   rx_ip_sof_s;\n  wire    [255:0]   rx_ip_data_s;\n  wire    [255:0]   rx_data_s;\n  wire              rx_sw_rstn_s;\n  wire              rx_sysref_s;\n"], ["hdl/projects/fmcjesdadc1/a5soc/system_top.v@248:258", "  wire              adc0_enable_b_s;\n  wire    [ 31:0]   adc0_data_b_s;\n  wire              adc0_dovf_s;\n  wire              adc1_enable_a_s;\n  wire    [ 31:0]   adc1_data_a_s;\n  wire              adc1_enable_b_s;\n  wire    [ 31:0]   adc1_data_b_s;\n  wire              adc1_dovf_s;\n  wire    [  3:0]   rx_ip_sof_s;\n  wire    [127:0]   rx_ip_data_s;\n  wire    [127:0]   rx_data_s;\n"], ["hdl/projects/fmcjesdadc1/a5soc/system_top.v@247:257", "  wire    [ 31:0]   adc0_data_a_s;\n  wire              adc0_enable_b_s;\n  wire    [ 31:0]   adc0_data_b_s;\n  wire              adc0_dovf_s;\n  wire              adc1_enable_a_s;\n  wire    [ 31:0]   adc1_data_a_s;\n  wire              adc1_enable_b_s;\n  wire    [ 31:0]   adc1_data_b_s;\n  wire              adc1_dovf_s;\n  wire    [  3:0]   rx_ip_sof_s;\n  wire    [127:0]   rx_ip_data_s;\n"], ["hdl/projects/fmcjesdadc1/a5soc/system_top.v@252:262", "  wire    [ 31:0]   adc1_data_a_s;\n  wire              adc1_enable_b_s;\n  wire    [ 31:0]   adc1_data_b_s;\n  wire              adc1_dovf_s;\n  wire    [  3:0]   rx_ip_sof_s;\n  wire    [127:0]   rx_ip_data_s;\n  wire    [127:0]   rx_data_s;\n  wire              rx_sw_rstn_s;\n  wire              rx_sysref_s;\n  wire              rx_err_s;\n  wire              rx_ready_s;\n"], ["hdl/projects/fmcjesdadc1/a5soc/system_top.v@249:259", "  wire    [ 31:0]   adc0_data_b_s;\n  wire              adc0_dovf_s;\n  wire              adc1_enable_a_s;\n  wire    [ 31:0]   adc1_data_a_s;\n  wire              adc1_enable_b_s;\n  wire    [ 31:0]   adc1_data_b_s;\n  wire              adc1_dovf_s;\n  wire    [  3:0]   rx_ip_sof_s;\n  wire    [127:0]   rx_ip_data_s;\n  wire    [127:0]   rx_data_s;\n  wire              rx_sw_rstn_s;\n"], ["hdl/projects/fmcjesdadc1/a5soc/system_top.v@254:264", "  wire    [ 31:0]   adc1_data_b_s;\n  wire              adc1_dovf_s;\n  wire    [  3:0]   rx_ip_sof_s;\n  wire    [127:0]   rx_ip_data_s;\n  wire    [127:0]   rx_data_s;\n  wire              rx_sw_rstn_s;\n  wire              rx_sysref_s;\n  wire              rx_err_s;\n  wire              rx_ready_s;\n  wire    [  3:0]   rx_rst_state_s;\n  wire              rx_lane_aligned_s;\n"], ["hdl/projects/fmcjesdadc1/a5soc/system_top.v@251:261", "  wire              adc1_enable_a_s;\n  wire    [ 31:0]   adc1_data_a_s;\n  wire              adc1_enable_b_s;\n  wire    [ 31:0]   adc1_data_b_s;\n  wire              adc1_dovf_s;\n  wire    [  3:0]   rx_ip_sof_s;\n  wire    [127:0]   rx_ip_data_s;\n  wire    [127:0]   rx_data_s;\n  wire              rx_sw_rstn_s;\n  wire              rx_sysref_s;\n  wire              rx_err_s;\n"], ["hdl/projects/fmcjesdadc1/a5soc/system_top.v@246:256", "  wire              adc0_enable_a_s;\n  wire    [ 31:0]   adc0_data_a_s;\n  wire              adc0_enable_b_s;\n  wire    [ 31:0]   adc0_data_b_s;\n  wire              adc0_dovf_s;\n  wire              adc1_enable_a_s;\n  wire    [ 31:0]   adc1_data_a_s;\n  wire              adc1_enable_b_s;\n  wire    [ 31:0]   adc1_data_b_s;\n  wire              adc1_dovf_s;\n  wire    [  3:0]   rx_ip_sof_s;\n"], ["hdl/projects/fmcjesdadc1/a5soc/system_top.v@253:263", "  wire              adc1_enable_b_s;\n  wire    [ 31:0]   adc1_data_b_s;\n  wire              adc1_dovf_s;\n  wire    [  3:0]   rx_ip_sof_s;\n  wire    [127:0]   rx_ip_data_s;\n  wire    [127:0]   rx_data_s;\n  wire              rx_sw_rstn_s;\n  wire              rx_sysref_s;\n  wire              rx_err_s;\n  wire              rx_ready_s;\n  wire    [  3:0]   rx_rst_state_s;\n"]], "Diff Content": {"Delete": [[255, "  wire              adc1_dovf_s;\n"]], "Add": []}}