{"Source Block": ["serv/rtl/serv_state.v@47:57@HdlStmAssign", "   wire running;\n\n   assign o_cnt_done = cnt_done;\n\n   //Update PC in RUN or TRAP states\n   assign o_ctrl_pc_en  = running | o_ctrl_trap;\n\n   assign o_csr_imm = (o_cnt < 5) ? i_rs1_addr[o_cnt[2:0]] : 1'b0;\n   assign o_alu_shamt_en = (o_cnt < 5) & (state == INIT);\n\n   assign o_mem_bytecnt = o_cnt[4:3];\n"], "Clone Blocks": [["serv/rtl/serv_state.v@54:64", "   assign o_csr_imm = (o_cnt < 5) ? i_rs1_addr[o_cnt[2:0]] : 1'b0;\n   assign o_alu_shamt_en = (o_cnt < 5) & (state == INIT);\n\n   assign o_mem_bytecnt = o_cnt[4:3];\n\n   assign cnt_en = (state != IDLE);\n   assign o_cnt_en   = cnt_en;\n\n   assign o_init = (state == INIT);\n\n   assign running = (state == RUN);\n"], ["serv/rtl/serv_state.v@52:62", "   assign o_ctrl_pc_en  = running | o_ctrl_trap;\n\n   assign o_csr_imm = (o_cnt < 5) ? i_rs1_addr[o_cnt[2:0]] : 1'b0;\n   assign o_alu_shamt_en = (o_cnt < 5) & (state == INIT);\n\n   assign o_mem_bytecnt = o_cnt[4:3];\n\n   assign cnt_en = (state != IDLE);\n   assign o_cnt_en   = cnt_en;\n\n   assign o_init = (state == INIT);\n"], ["serv/rtl/serv_state.v@50:60", "\n   //Update PC in RUN or TRAP states\n   assign o_ctrl_pc_en  = running | o_ctrl_trap;\n\n   assign o_csr_imm = (o_cnt < 5) ? i_rs1_addr[o_cnt[2:0]] : 1'b0;\n   assign o_alu_shamt_en = (o_cnt < 5) & (state == INIT);\n\n   assign o_mem_bytecnt = o_cnt[4:3];\n\n   assign cnt_en = (state != IDLE);\n   assign o_cnt_en   = cnt_en;\n"], ["serv/rtl/serv_state.v@49:59", "   assign o_cnt_done = cnt_done;\n\n   //Update PC in RUN or TRAP states\n   assign o_ctrl_pc_en  = running | o_ctrl_trap;\n\n   assign o_csr_imm = (o_cnt < 5) ? i_rs1_addr[o_cnt[2:0]] : 1'b0;\n   assign o_alu_shamt_en = (o_cnt < 5) & (state == INIT);\n\n   assign o_mem_bytecnt = o_cnt[4:3];\n\n   assign cnt_en = (state != IDLE);\n"]], "Diff Content": {"Delete": [[52, "   assign o_ctrl_pc_en  = running | o_ctrl_trap;\n"]], "Add": [[52, "   assign o_ctrl_pc_en  = running | (state == TRAP);\n"]]}}