{"Source Block": ["hdl/library/sysid_rom/sysid_rom.v@9:21@HdlStmProcess", "  input        [ROM_ADDR_BITS-1:0]  rom_addr,\n  output  reg  [ROM_WIDTH-1:0]      rom_data);\n\nreg [ROM_WIDTH-1:0] lut_rom [(2**ROM_ADDR_BITS)-1:0];\n\ninitial begin\n  $readmemh(PATH_TO_FILE, lut_rom, 0, (2**ROM_ADDR_BITS)-1);\nend\n\nalways @(posedge clk) begin\n  rom_data = lut_rom[rom_addr];\nend\n\n"], "Clone Blocks": [["hdl/library/sysid_rom/sysid_rom.v@7:17", "\n  input                             clk,\n  input        [ROM_ADDR_BITS-1:0]  rom_addr,\n  output  reg  [ROM_WIDTH-1:0]      rom_data);\n\nreg [ROM_WIDTH-1:0] lut_rom [(2**ROM_ADDR_BITS)-1:0];\n\ninitial begin\n  $readmemh(PATH_TO_FILE, lut_rom, 0, (2**ROM_ADDR_BITS)-1);\nend\n\n"]], "Diff Content": {"Delete": [[14, "initial begin\n"], [15, "  $readmemh(PATH_TO_FILE, lut_rom, 0, (2**ROM_ADDR_BITS)-1);\n"], [16, "end\n"]], "Add": [[16, "  initial begin\n"], [16, "    $readmemh(PATH_TO_FILE, lut_rom, 0, (2**ROM_ADDR_BITS)-1);\n"], [16, "  end\n"]]}}