{"Source Block": ["hdl/library/util_pack/util_cpack2/util_cpack2.v@194:204@HdlIdDef", "   NUM_OF_CHANNELS > 2 ? 4 :\n   NUM_OF_CHANNELS > 1 ? 2 : 1;\n\n/* FIXME: Find out how to do this in the IP-XACT */\n\nwire [REAL_NUM_OF_CHANNELS-1:0] enable;\nwire [63:0] enable_s;\nwire [CHANNEL_DATA_WIDTH*REAL_NUM_OF_CHANNELS-1:0] fifo_wr_data;\nwire [CHANNEL_DATA_WIDTH*64-1:0] fifo_wr_data_s;\n\nassign enable_s = {\n"], "Clone Blocks": [["hdl/library/util_pack/util_upack2/util_upack2.v@195:205", "   NUM_OF_CHANNELS > 2 ? 4 :\n   NUM_OF_CHANNELS > 1 ? 2 : 1;\n\n/* FIXME: Find out how to do this in the IP-XACT */\n\nwire [63:0] enable_s;\nwire [CHANNEL_DATA_WIDTH*REAL_NUM_OF_CHANNELS-1:0] fifo_rd_data;\nwire [CHANNEL_DATA_WIDTH*64-1:0] fifo_rd_data_s;\n\nutil_upack2_impl #(\n  .NUM_OF_CHANNELS(REAL_NUM_OF_CHANNELS),\n"]], "Diff Content": {"Delete": [[199, "wire [REAL_NUM_OF_CHANNELS-1:0] enable;\n"]], "Add": []}}