{"Source Block": ["hdl/library/axi_dmac/dest_fifo_inf.v@76:86@HdlIdDef", "`include \"inc_id.vh\"\n\nreg active = 1'b0;\n\n/* Last beat of the burst */\nwire fifo_last_beat;\n/* Last beat of the segment */\nwire fifo_eot_beat;\n\nassign enabled = enable;\nassign fifo_ready = en & (fifo_valid | ~enable);\n"], "Clone Blocks": [["hdl/library/axi_dmac/dest_fifo_inf.v@78:88", "reg active = 1'b0;\n\n/* Last beat of the burst */\nwire fifo_last_beat;\n/* Last beat of the segment */\nwire fifo_eot_beat;\n\nassign enabled = enable;\nassign fifo_ready = en & (fifo_valid | ~enable);\n\n/* fifo_last == 1'b1 implies fifo_valid == 1'b1 */\n"]], "Diff Content": {"Delete": [[81, "wire fifo_last_beat;\n"]], "Add": []}}