{"Source Block": ["hdl/library/jesd204/jesd204_common/jesd204_lmfc.v@87:97@HdlIdDef", "reg sysref_captured;\n\n/* lmfc_octet_counter = lmfc_counter * (char_clock_rate / device_clock_rate) */\nreg [7:0] lmfc_counter_next = 'h00;\n\nreg lmfc_clk_p1 = 1'b1;\n\nreg lmfc_active = 1'b0;\n\nalways @(posedge clk) begin\n  sysref_r <= sysref;\n"], "Clone Blocks": [["hdl/library/jesd204/jesd204_common/jesd204_lmfc.v@85:95", "reg sysref_d3 = 1'b0;\n\nreg sysref_captured;\n\n/* lmfc_octet_counter = lmfc_counter * (char_clock_rate / device_clock_rate) */\nreg [7:0] lmfc_counter_next = 'h00;\n\nreg lmfc_clk_p1 = 1'b1;\n\nreg lmfc_active = 1'b0;\n\n"], ["hdl/library/jesd204/jesd204_common/jesd204_lmfc.v@89:99", "/* lmfc_octet_counter = lmfc_counter * (char_clock_rate / device_clock_rate) */\nreg [7:0] lmfc_counter_next = 'h00;\n\nreg lmfc_clk_p1 = 1'b1;\n\nreg lmfc_active = 1'b0;\n\nalways @(posedge clk) begin\n  sysref_r <= sysref;\nend\n\n"]], "Diff Content": {"Delete": [[92, "reg lmfc_clk_p1 = 1'b1;\n"]], "Add": []}}