{"Source Block": ["oh/common/hdl/oh_fifo_generic.v@66:90@HdlStmProcess", "       end\n     else if(rd_en_sync) \n       wr_count[AW-1:0]<= wr_count[AW-1:0] - 'd1;\t\n\n   // read side state machine\n   always @ ( posedge rd_clk or negedge nreset) \n     if(!nreset) \n       begin\t   \n          rd_addr[AW-1:0]   <= 'd0;\n\t  rd_count[AW-1:0]  <= 'd0;\n       end \n     else if(rd_en & wr_en_sync) \n       rd_addr[AW-1:0] <= rd_addr[AW-1:0] + 'd1;\n     else if(rd_en) \n       begin\n\t  rd_addr[AW-1:0] <= rd_addr[AW-1:0]  + 'd1;\n\t  rd_count[AW-1:0] <= rd_count[AW-1:0] - 'd1;\t\n       end\n     else if(wr_en_sync) \n       rd_count[AW-1:0] <= rd_count[AW-1:0] + 'd1;\t\n         \n   // clock domain synchronizers\n   oh_dsync wr_sync(.dout (wr_en_sync),\n\t\t    .clk  (rd_clk),\n\t\t    .din  (wr_en));\n"], "Clone Blocks": [["oh/common/hdl/oh_fifo_generic.v@49:73", "   assign empty     = (rd_count[AW-1:0] == 'b0);\n   assign full      = (wr_count[AW-1:0] == DEPTH);\n   assign prog_full = (wr_count[AW-1:0] >= PROG_FULL);   \n\n   // write side state machine\n   always @ ( posedge wr_clk or negedge nreset) \n     if(!nreset) \n       begin\t   \n          wr_addr[AW-1:0]   <= 'd0;\n\t  wr_count[AW-1:0]  <= 'd0;\n       end \n     else if(wr_en & rd_en_sync) \n\t  wr_addr[AW-1:0] <= wr_addr[AW-1:0] + 'd1;\n     else if(wr_en) \n       begin\n\t  wr_addr[AW-1:0] <= wr_addr[AW-1:0]  + 'd1;\n\t  wr_count[AW-1:0]<= wr_count[AW-1:0] + 'd1;\t\n       end\n     else if(rd_en_sync) \n       wr_count[AW-1:0]<= wr_count[AW-1:0] - 'd1;\t\n\n   // read side state machine\n   always @ ( posedge rd_clk or negedge nreset) \n     if(!nreset) \n       begin\t   \n"]], "Diff Content": {"Delete": [[73, "       begin\t   \n"], [74, "          rd_addr[AW-1:0]   <= 'd0;\n"], [75, "\t  rd_count[AW-1:0]  <= 'd0;\n"], [76, "       end \n"], [77, "     else if(rd_en & wr_en_sync) \n"], [78, "       rd_addr[AW-1:0] <= rd_addr[AW-1:0] + 'd1;\n"], [80, "       begin\n"], [81, "\t  rd_addr[AW-1:0] <= rd_addr[AW-1:0]  + 'd1;\n"], [82, "\t  rd_count[AW-1:0] <= rd_count[AW-1:0] - 'd1;\t\n"], [83, "       end\n"], [84, "     else if(wr_en_sync) \n"], [85, "       rd_count[AW-1:0] <= rd_count[AW-1:0] + 'd1;\t\n"]], "Add": [[78, "       rd_addr[AW:0] <= 'd0;   \n"]]}}