{"Source Block": ["oh/elink/dv/elink_e16_model.v@2758:2768@HdlStmAssign", "   /********************************************/\n   /*Splitting Vector Into Components          */\n   /********************************************/\n   assign mesh_write_cvre           = fifo_data_out_cvre[0];\n   assign mesh_read_cvre            = fifo_data_out_cvre[1];\n   assign mesh_datamode_cvre[1:0]   = fifo_data_out_cvre[3:2];\n   assign mesh_ctrlmode_cvre[3:0]   = fifo_data_out_cvre[7:4];\n   assign mesh_reserved_cvre[7:0]   = fifo_data_out_cvre[15:8];\n   assign mesh_data_cvre[MDW-1:0]   = fifo_data_out_cvre[47:16];\n   assign mesh_dst_addr_cvre[AW-1:0]= fifo_data_out_cvre[79:48];\n   assign mesh_src_addr_cvre[AW-1:0]= fifo_data_out_cvre[111:80];\n"], "Clone Blocks": [["oh/elink/dv/elink_e16_model.v@2763:2773", "   assign mesh_datamode_cvre[1:0]   = fifo_data_out_cvre[3:2];\n   assign mesh_ctrlmode_cvre[3:0]   = fifo_data_out_cvre[7:4];\n   assign mesh_reserved_cvre[7:0]   = fifo_data_out_cvre[15:8];\n   assign mesh_data_cvre[MDW-1:0]   = fifo_data_out_cvre[47:16];\n   assign mesh_dst_addr_cvre[AW-1:0]= fifo_data_out_cvre[79:48];\n   assign mesh_src_addr_cvre[AW-1:0]= fifo_data_out_cvre[111:80];\n\n\n   /********************************************/\n   /*Address Decoding                          */\n   /********************************************/\n"], ["oh/elink/dv/elink_e16_model.v@2759:2769", "   /*Splitting Vector Into Components          */\n   /********************************************/\n   assign mesh_write_cvre           = fifo_data_out_cvre[0];\n   assign mesh_read_cvre            = fifo_data_out_cvre[1];\n   assign mesh_datamode_cvre[1:0]   = fifo_data_out_cvre[3:2];\n   assign mesh_ctrlmode_cvre[3:0]   = fifo_data_out_cvre[7:4];\n   assign mesh_reserved_cvre[7:0]   = fifo_data_out_cvre[15:8];\n   assign mesh_data_cvre[MDW-1:0]   = fifo_data_out_cvre[47:16];\n   assign mesh_dst_addr_cvre[AW-1:0]= fifo_data_out_cvre[79:48];\n   assign mesh_src_addr_cvre[AW-1:0]= fifo_data_out_cvre[111:80];\n\n"], ["oh/elink/dv/elink_e16_model.v@2756:2766", "   wire           request_cvre;\n   \n   /********************************************/\n   /*Splitting Vector Into Components          */\n   /********************************************/\n   assign mesh_write_cvre           = fifo_data_out_cvre[0];\n   assign mesh_read_cvre            = fifo_data_out_cvre[1];\n   assign mesh_datamode_cvre[1:0]   = fifo_data_out_cvre[3:2];\n   assign mesh_ctrlmode_cvre[3:0]   = fifo_data_out_cvre[7:4];\n   assign mesh_reserved_cvre[7:0]   = fifo_data_out_cvre[15:8];\n   assign mesh_data_cvre[MDW-1:0]   = fifo_data_out_cvre[47:16];\n"], ["oh/elink/dv/elink_e16_model.v@2760:2770", "   /********************************************/\n   assign mesh_write_cvre           = fifo_data_out_cvre[0];\n   assign mesh_read_cvre            = fifo_data_out_cvre[1];\n   assign mesh_datamode_cvre[1:0]   = fifo_data_out_cvre[3:2];\n   assign mesh_ctrlmode_cvre[3:0]   = fifo_data_out_cvre[7:4];\n   assign mesh_reserved_cvre[7:0]   = fifo_data_out_cvre[15:8];\n   assign mesh_data_cvre[MDW-1:0]   = fifo_data_out_cvre[47:16];\n   assign mesh_dst_addr_cvre[AW-1:0]= fifo_data_out_cvre[79:48];\n   assign mesh_src_addr_cvre[AW-1:0]= fifo_data_out_cvre[111:80];\n\n\n"], ["oh/elink/dv/elink_e16_model.v@2761:2771", "   assign mesh_write_cvre           = fifo_data_out_cvre[0];\n   assign mesh_read_cvre            = fifo_data_out_cvre[1];\n   assign mesh_datamode_cvre[1:0]   = fifo_data_out_cvre[3:2];\n   assign mesh_ctrlmode_cvre[3:0]   = fifo_data_out_cvre[7:4];\n   assign mesh_reserved_cvre[7:0]   = fifo_data_out_cvre[15:8];\n   assign mesh_data_cvre[MDW-1:0]   = fifo_data_out_cvre[47:16];\n   assign mesh_dst_addr_cvre[AW-1:0]= fifo_data_out_cvre[79:48];\n   assign mesh_src_addr_cvre[AW-1:0]= fifo_data_out_cvre[111:80];\n\n\n   /********************************************/\n"], ["oh/elink/dv/elink_e16_model.v@2762:2772", "   assign mesh_read_cvre            = fifo_data_out_cvre[1];\n   assign mesh_datamode_cvre[1:0]   = fifo_data_out_cvre[3:2];\n   assign mesh_ctrlmode_cvre[3:0]   = fifo_data_out_cvre[7:4];\n   assign mesh_reserved_cvre[7:0]   = fifo_data_out_cvre[15:8];\n   assign mesh_data_cvre[MDW-1:0]   = fifo_data_out_cvre[47:16];\n   assign mesh_dst_addr_cvre[AW-1:0]= fifo_data_out_cvre[79:48];\n   assign mesh_src_addr_cvre[AW-1:0]= fifo_data_out_cvre[111:80];\n\n\n   /********************************************/\n   /*Address Decoding                          */\n"], ["oh/elink/dv/elink_e16_model.v@2757:2767", "   \n   /********************************************/\n   /*Splitting Vector Into Components          */\n   /********************************************/\n   assign mesh_write_cvre           = fifo_data_out_cvre[0];\n   assign mesh_read_cvre            = fifo_data_out_cvre[1];\n   assign mesh_datamode_cvre[1:0]   = fifo_data_out_cvre[3:2];\n   assign mesh_ctrlmode_cvre[3:0]   = fifo_data_out_cvre[7:4];\n   assign mesh_reserved_cvre[7:0]   = fifo_data_out_cvre[15:8];\n   assign mesh_data_cvre[MDW-1:0]   = fifo_data_out_cvre[47:16];\n   assign mesh_dst_addr_cvre[AW-1:0]= fifo_data_out_cvre[79:48];\n"]], "Diff Content": {"Delete": [[2763, "   assign mesh_datamode_cvre[1:0]   = fifo_data_out_cvre[3:2];\n"]], "Add": []}}