{"Source Block": ["hdl/library/spi_engine/spi_engine_execution/spi_engine_execution.v@243:258@HdlStmProcess", "\nwire sleep_counter_compare = sleep_counter == cmd_d1[7:0] && clk_div_last == 1'b1;\nwire cs_sleep_counter_compare = cs_sleep_counter == cmd_d1[9:8] && clk_div_last == 1'b1;\nwire cs_sleep_counter_compare2 = cs_sleep_counter2 == {cmd_d1[9:8],1'b1} && clk_div_last == 1'b1;\n\nalways @(posedge clk) begin\n  if (idle == 1'b1)\n    counter <= 'h00;\n  else if (clk_div_last == 1'b1 && wait_for_io == 1'b0)\n    counter <= counter + (transfer_active ? 'h1 : 'h10);\nend\n\nalways @(posedge clk) begin\n  if (resetn == 1'b0) begin\n    idle <= 1'b1;\n  end else begin\n"], "Clone Blocks": [["hdl/library/spi_engine/spi_engine_execution/spi_engine_execution.v@241:251", "end\n\n\nwire sleep_counter_compare = sleep_counter == cmd_d1[7:0] && clk_div_last == 1'b1;\nwire cs_sleep_counter_compare = cs_sleep_counter == cmd_d1[9:8] && clk_div_last == 1'b1;\nwire cs_sleep_counter_compare2 = cs_sleep_counter2 == {cmd_d1[9:8],1'b1} && clk_div_last == 1'b1;\n\nalways @(posedge clk) begin\n  if (idle == 1'b1)\n    counter <= 'h00;\n  else if (clk_div_last == 1'b1 && wait_for_io == 1'b0)\n"], ["hdl/library/spi_engine/spi_engine_execution/spi_engine_execution.v@228:246", "    clk_div_last <= 1'b1;\n  else\n    clk_div_last <= 1'b0;\nend\n\nalways @(posedge clk) begin\n  if (clk_div_last == 1'b1 || idle == 1'b1 || wait_for_io == 1'b1) begin\n    clk_div_counter <= clk_div;\n    trigger <= 1'b1;\n  end else begin\n    clk_div_counter <= clk_div_counter - 1'b1;\n    trigger <= 1'b0;\n  end\nend\n\n\nwire sleep_counter_compare = sleep_counter == cmd_d1[7:0] && clk_div_last == 1'b1;\nwire cs_sleep_counter_compare = cs_sleep_counter == cmd_d1[9:8] && clk_div_last == 1'b1;\nwire cs_sleep_counter_compare2 = cs_sleep_counter2 == {cmd_d1[9:8],1'b1} && clk_div_last == 1'b1;\n"]], "Diff Content": {"Delete": [[249, "  if (idle == 1'b1)\n"], [251, "  else if (clk_div_last == 1'b1 && wait_for_io == 1'b0)\n"], [252, "    counter <= counter + (transfer_active ? 'h1 : 'h10);\n"]], "Add": [[249, "  if (idle == 1'b1) begin\n"], [252, "  end else if (clk_div_last == 1'b1 && wait_for_io == 1'b0) begin\n"], [252, "    if (bit_counter == word_length) begin\n"], [252, "        counter <= (counter & BIT_COUNTER_CLEAR) + (transfer_active ? 'h1 : 'h10) + BIT_COUNTER_CARRY;\n"], [252, "    end else begin\n"], [252, "      counter <= counter + (transfer_active ? 'h1 : 'h10);\n"], [252, "    end\n"], [252, "  end\n"]]}}