{"Source Block": ["oh/elink/hdl/erx_core.v@91:101@HdlIdDef", "   wire \trxrr_full;\n   wire \trxrd_full;\n   wire \trxrd_empty;\n   wire \trxwr_empty;\n   wire \trxrr_empty;\n   wire [103:0] edma_packet;\t\t// From edma of edma.v, ...\n   \n\n   /**************************************************************/\n   /*ELINK PROTOCOL LOGIC                                        */\n   /**************************************************************/\n"], "Clone Blocks": [["oh/elink/hdl/erx_core.v@90:100", "   wire \trxwr_full;\n   wire \trxrr_full;\n   wire \trxrd_full;\n   wire \trxrd_empty;\n   wire \trxwr_empty;\n   wire \trxrr_empty;\n   wire [103:0] edma_packet;\t\t// From edma of edma.v, ...\n   \n\n   /**************************************************************/\n   /*ELINK PROTOCOL LOGIC                                        */\n"], ["oh/elink/hdl/erx_core.v@89:99", "   wire [15:0] \trx_status;\n   wire \trxwr_full;\n   wire \trxrr_full;\n   wire \trxrd_full;\n   wire \trxrd_empty;\n   wire \trxwr_empty;\n   wire \trxrr_empty;\n   wire [103:0] edma_packet;\t\t// From edma of edma.v, ...\n   \n\n   /**************************************************************/\n"]], "Diff Content": {"Delete": [[96, "   wire [103:0] edma_packet;\t\t// From edma of edma.v, ...\n"]], "Add": [[96, "   wire [8:0] \t\tgpio_datain;\n"], [96, "   wire [15:0] \t\trx_status;\n"], [96, "   wire \t\trxwr_full;\n"], [96, "   wire \t\trxrr_full;\n"], [96, "   wire \t\trxrd_full;\n"], [96, "   wire \t\trxrd_empty;\n"], [96, "   wire \t\trxwr_empty;\n"], [96, "   wire \t\trxrr_empty;\n"], [96, "   wire [103:0] \tedma_packet;\n"]]}}