{"Source Block": ["hdl/library/common/ad_datafmt.v@86:98@HdlStmIf", "  assign type_s = dfmt_enable & dfmt_type;\n  assign signext_s = dfmt_enable & dfmt_se;\n  assign sign_s = signext_s & (type_s ^ data[(DATA_WIDTH-1)]);\n\n  generate\n  if (DATA_WIDTH < 16) begin\n  assign data_out_s[15:DATA_WIDTH] = {(16-DATA_WIDTH){sign_s}};\n  end\n  endgenerate\n  \n  assign data_out_s[(DATA_WIDTH-1)] = type_s ^ data[(DATA_WIDTH-1)];\n  assign data_out_s[(DATA_WIDTH-2):0] = data[(DATA_WIDTH-2):0];\n\n"], "Clone Blocks": [], "Diff Content": {"Delete": [[92, "  assign data_out_s[15:DATA_WIDTH] = {(16-DATA_WIDTH){sign_s}};\n"]], "Add": [[92, "    wire signext_s;\n"], [92, "    wire sign_s;\n"], [92, "    assign signext_s = dfmt_enable & dfmt_se;\n"], [92, "    assign sign_s = signext_s & (type_s ^ data[(DATA_WIDTH-1)]);\n"], [92, "    assign data_out_s[15:DATA_WIDTH] = {(16-DATA_WIDTH){sign_s}};\n"]]}}