{"Source Block": ["hdl/library/prcfg/qpsk/prcfg_dac.v@118:128@HdlStmAssign", "      pn_data = pn(pn_data);\n    end\n  end\n\n  // data source for the modulator\n  assign dac_data = (mode == 1) ? pn_data : src_dac_ddata[ 1: 0];\n\n  // modulated data\n  assign dac_data_mode1_2 = { dac_data_fltr_q, dac_data_fltr_i };\n\n  // qpsk modulator\n"], "Clone Blocks": [["hdl/library/prcfg/qpsk/prcfg_dac.v@121:131", "\n  // data source for the modulator\n  assign dac_data = (mode == 1) ? pn_data : src_dac_ddata[ 1: 0];\n\n  // modulated data\n  assign dac_data_mode1_2 = { dac_data_fltr_q, dac_data_fltr_i };\n\n  // qpsk modulator\n  qpsk_mod i_qpsk_mod (\n    .clk(clk),\n    .data_input(dac_data),\n"], ["hdl/library/prcfg/qpsk/prcfg_dac.v@111:125", "\n  // pass through mode\n  assign dac_data_mode0 = src_dac_ddata;\n\n  // prbs geenration\n  always @(posedge clk) begin\n    if(dst_dac_drd == 1) begin\n      pn_data = pn(pn_data);\n    end\n  end\n\n  // data source for the modulator\n  assign dac_data = (mode == 1) ? pn_data : src_dac_ddata[ 1: 0];\n\n  // modulated data\n"]], "Diff Content": {"Delete": [[123, "  assign dac_data = (mode == 1) ? pn_data : src_dac_ddata[ 1: 0];\n"]], "Add": [[123, "  assign dac_data = (mode == 1) ? pn_data[ 1:0] : src_dac_ddata[ 1:0];\n"]]}}